yeabm25/__init__.py
yeabm25/bm25.py
yeabm25-0.1.4.dist-info/LICENSE
yeabm25-0.1.4.dist-info/METADATA
yeabm25-0.1.4.dist-info/WHEEL
yeabm25-0.1.4.dist-info/top_level.txt
yeabm25-0.1.4.dist-info/RECORD
