Metadata-Version: 2.1
Name: yeabm25
Version: 0.1.4
Summary: Yet Another BM25 algorithm implementation with update method, so that you dont need to fit on old + new documents.
Author-email: Demir Tonchev <{surname}.{name}@gmail.com>
License: Apache License
Project-URL: Homepage, https://github.com/DemirTonchev/yeabm25
Keywords: text,bm25,dense vector embeddings,information retrieval,hybrid search
Requires-Python: >=3.10
License-File: LICENSE
Requires-Dist: numpy >=1.26
Provides-Extra: test
Requires-Dist: pytest ; extra == 'test'
Requires-Dist: coverage ; extra == 'test'
